face_recognition_and_drowsiness_detection/__init__.py
face_recognition_and_drowsiness_detection/lcms.py
face_recognition_and_drowsiness_detection-0.1.1.dist-info/AUTHORS.rst
face_recognition_and_drowsiness_detection-0.1.1.dist-info/LICENSE
face_recognition_and_drowsiness_detection-0.1.1.dist-info/METADATA
face_recognition_and_drowsiness_detection-0.1.1.dist-info/WHEEL
face_recognition_and_drowsiness_detection-0.1.1.dist-info/entry_points.txt
face_recognition_and_drowsiness_detection-0.1.1.dist-info/top_level.txt
face_recognition_and_drowsiness_detection-0.1.1.dist-info/RECORD
