Metadata-Version: 2.1
Name: face-recognition-and-drowsiness-detection
Version: 0.1.1
Summary: Python Boilerplate contains all the boilerplate you need to create a Python package.
Home-page: https://github.com/Pradip240/face_recognition_and_drowsiness_detection
Author: Pradip Solanki
Author-email: solankipms@gmail.com
License: MIT license
Keywords: face_recognition_and_drowsiness_detection
Platform: UNKNOWN
Classifier: Development Status :: 2 - Pre-Alpha
Classifier: Intended Audience :: Developers
Classifier: License :: OSI Approved :: MIT License
Classifier: Natural Language :: English
Classifier: Programming Language :: Python :: 3
Classifier: Programming Language :: Python :: 3.6
Classifier: Programming Language :: Python :: 3.7
Classifier: Programming Language :: Python :: 3.8
Requires-Python: >=3.6
License-File: LICENSE
License-File: AUTHORS.rst
Requires-Dist: altair (==4.1.0)
Requires-Dist: argon2-cffi (==20.1.0)
Requires-Dist: astor (==0.8.1)
Requires-Dist: async-generator (==1.10)
Requires-Dist: attrs (==21.1.0)
Requires-Dist: backcall (==0.2.0)
Requires-Dist: base58 (==2.1.0)
Requires-Dist: beepy (==1.0.7)
Requires-Dist: bleach (==3.3.0)
Requires-Dist: blinker (==1.4)
Requires-Dist: cachetools (==4.2.2)
Requires-Dist: certifi (==2020.12.5)
Requires-Dist: cffi (==1.14.5)
Requires-Dist: chardet (==4.0.0)
Requires-Dist: click (==7.1.2)
Requires-Dist: cmake (==3.18.4.post1)
Requires-Dist: colorama (==0.4.4)
Requires-Dist: decorator (==5.0.7)
Requires-Dist: defusedxml (==0.7.1)
Requires-Dist: dlib (==19.22.0)
Requires-Dist: entrypoints (==0.3)
Requires-Dist: face-recognition (==1.3.0)
Requires-Dist: face-recognition-models (==0.3.0)
Requires-Dist: gitdb (==4.0.7)
Requires-Dist: GitPython (==3.1.14)
Requires-Dist: idna (==2.10)
Requires-Dist: ipykernel (==5.5.4)
Requires-Dist: ipython (==7.23.1)
Requires-Dist: ipython-genutils (==0.2.0)
Requires-Dist: ipywidgets (==7.6.3)
Requires-Dist: jedi (==0.18.0)
Requires-Dist: Jinja2 (==2.11.3)
Requires-Dist: jsonschema (==3.2.0)
Requires-Dist: jupyter-client (==6.1.12)
Requires-Dist: jupyter-core (==4.7.1)
Requires-Dist: jupyterlab-pygments (==0.1.2)
Requires-Dist: jupyterlab-widgets (==1.0.0)
Requires-Dist: MarkupSafe (==1.1.1)
Requires-Dist: matplotlib-inline (==0.1.2)
Requires-Dist: mistune (==0.8.4)
Requires-Dist: nbclient (==0.5.3)
Requires-Dist: nbconvert (==6.0.7)
Requires-Dist: nbformat (==5.1.3)
Requires-Dist: nest-asyncio (==1.5.1)
Requires-Dist: notebook (==6.3.0)
Requires-Dist: numpy (==1.20.2)
Requires-Dist: opencv-python (==4.5.1.48)
Requires-Dist: packaging (==20.9)
Requires-Dist: pandas (==1.2.4)
Requires-Dist: pandocfilters (==1.4.3)
Requires-Dist: parso (==0.8.2)
Requires-Dist: pickleshare (==0.7.5)
Requires-Dist: Pillow (==8.2.0)
Requires-Dist: prometheus-client (==0.10.1)
Requires-Dist: prompt-toolkit (==3.0.18)
Requires-Dist: protobuf (==3.15.8)
Requires-Dist: pycparser (==2.20)
Requires-Dist: pydeck (==0.6.2)
Requires-Dist: Pygments (==2.9.0)
Requires-Dist: pyparsing (==2.4.7)
Requires-Dist: pyrsistent (==0.17.3)
Requires-Dist: python-dateutil (==2.8.1)
Requires-Dist: pytz (==2021.1)
Requires-Dist: pywin32 (==300)
Requires-Dist: pywinpty (==1.0.1)
Requires-Dist: pyzmq (==22.0.3)
Requires-Dist: requests (==2.25.1)
Requires-Dist: Send2Trash (==1.5.0)
Requires-Dist: simpleaudio (==1.0.4)
Requires-Dist: six (==1.16.0)
Requires-Dist: smmap (==4.0.0)
Requires-Dist: streamlit (==0.81.1)
Requires-Dist: terminado (==0.9.4)
Requires-Dist: testpath (==0.4.4)
Requires-Dist: toml (==0.10.2)
Requires-Dist: toolz (==0.11.1)
Requires-Dist: tornado (==6.1)
Requires-Dist: traitlets (==5.0.5)
Requires-Dist: tzlocal (==2.1)
Requires-Dist: urllib3 (==1.26.4)
Requires-Dist: validators (==0.18.2)
Requires-Dist: watchdog (==2.1.0)
Requires-Dist: wcwidth (==0.2.5)
Requires-Dist: webencodings (==0.5.1)
Requires-Dist: widgetsnbextension (==3.5.1)
Requires-Dist: wincertstore (==0.2)
